{
	"info": {
		"_postman_id": "6df46deb-89bc-4e39-b175-61dfcd2b726a",
		"name": "Toposervice",
		"schema": "https://schema.getpostman.com/json/collection/v2.1.0/collection.json",
		"_exporter_id": "24772546"
	},
	"item": [
		{
			"name": "Get city",
			"request": {
				"method": "GET",
				"header": [],
				"url": {
					"raw": "http://localhost:8081/api/v1/topographicdetails/Sevilla",
					"protocol": "http",
					"host": [
						"localhost"
					],
					"port": "8081",
					"path": [
						"api",
						"v1",
						"topographicdetails",
						"Sevilla"
					]
				}
			},
			"response": []
		},
		{
			"name": "Get city error",
			"request": {
				"method": "GET",
				"header": [],
				"url": {
					"raw": "http://localhost:8081/api/v1/topographicdetails/Tokyo",
					"protocol": "http",
					"host": [
						"localhost"
					],
					"port": "8081",
					"path": [
						"api",
						"v1",
						"topographicdetails",
						"Tokyo"
					]
				}
			},
			"response": []
		}
	]
}